{
    "packages": {
        "array/editor": {
            "1.1.0": {
                "name": "array/editor",
                "version": "1.1.0",
                "dist": {
                    "type": "zip",
                    "url": "http://wordpress.org/themes/download/editor.1.1.0.zip"
                },
                "require": {
                    "kucrut/wordpress": ">=3.8"
                },
                "type": "wordpress-theme",
                "license": [
                    "GPL-2.0+"
                ],
                "authors": [
                    {
                        "name": "Array",
                        "homepage": "http://array.is/"
                    }
                ]
            }
        },
        "automattic/pictorico": {
            "1.06": {
                "name": "automattic/pictorico",
                "version": "1.06",
                "dist": {
                    "type": "zip",
                    "url": "http://wordpress.org/themes/download/pictorico.1.06.zip"
                },
                "require": {
                    "kucrut/wordpress": ">=3.8"
                },
                "type": "wordpress-theme",
                "license": [
                    "GPL-2.0+"
                ],
                "authors": [
                    {
                        "name": "Automattic",
                        "homepage": "http://automattic.com/"
                    }
                ]
            }
        },
        "automattic/fictive": {
            "1.1": {
                "name": "automattic/fictive",
                "version": "1.1",
                "dist": {
                    "type": "zip",
                    "url": "http://wordpress.org/themes/download/fictive.1.1.zip"
                },
                "require": {
                    "kucrut/wordpress": ">=3.8"
                },
                "type": "wordpress-theme",
                "license": [
                    "GPL-2.0+"
                ],
                "authors": [
                    {
                        "name": "Automattic",
                        "homepage": "http://automattic.com/"
                    }
                ]
            }
        },
        "automattic/writr": {
            "1.0.8": {
                "name": "automattic/writr",
                "version": "1.0.8",
                "dist": {
                    "type": "zip",
                    "url": "http://wordpress.org/themes/download/writr.1.0.8.zip"
                },
                "require": {
                    "kucrut/wordpress": ">=3.8"
                },
                "type": "wordpress-theme",
                "license": [
                    "GPL-2.0+"
                ],
                "authors": [
                    {
                        "name": "Automattic",
                        "homepage": "http://automattic.com/"
                    }
                ]
            }
        },
        "automattic/hex": {
            "1.0.1": {
                "name": "automattic/hex",
                "version": "1.0.1",
                "dist": {
                    "type": "zip",
                    "url": "http://wordpress.org/themes/download/hex.1.0.1.zip"
                },
                "require": {
                    "kucrut/wordpress": ">=3.8"
                },
                "type": "wordpress-theme",
                "license": [
                    "GPL-2.0+"
                ],
                "authors": [
                    {
                        "name": "Automattic",
                        "homepage": "http://automattic.com/"
                    }
                ]
            }
        },
        "automattic/illustratr": {
            "1.1.4": {
                "name": "automattic/illustratr",
                "version": "1.1.4",
                "dist": {
                    "type": "zip",
                    "url": "http://wordpress.org/themes/download/illustratr.1.1.4.zip"
                },
                "require": {
                    "kucrut/wordpress": ">=3.8"
                },
                "type": "wordpress-theme",
                "license": [
                    "GPL-2.0+"
                ],
                "authors": [
                    {
                        "name": "Automattic",
                        "homepage": "http://automattic.com/"
                    }
                ]
            }
        },
        "kopatheme/forceful-lite": {
            "1.0.8": {
                "name": "kopatheme/forceful-lite",
                "version": "1.0.8",
                "dist": {
                    "type": "zip",
                    "url": "http://wordpress.org/themes/download/forceful-lite.1.0.8.zip"
                },
                "require": {
                    "kucrut/wordpress": ">=3.8"
                },
                "type": "wordpress-theme",
                "license": [
                    "GPL-2.0+"
                ],
                "authors": [
                    {
                        "name": "Kopa Theme",
                        "homepage": "http://profiles.wordpress.org/kopatheme/"
                    }
                ]
            }
        },
        "AlxMedia/hueman": {
            "1.4.5": {
                "name": "AlxMedia/hueman",
                "version": "1.4.5",
                "dist": {
                    "type": "zip",
                    "url": "http://wordpress.org/themes/download/hueman.1.4.5.zip"
                },
                "require": {
                    "kucrut/wordpress": ">=3.8"
                },
                "type": "wordpress-theme",
                "license": [
                    "GPL-2.0+"
                ],
                "authors": [
                    {
                        "name": "Alexander Agnarson",
                        "homepage": "http://profiles.wordpress.org/AlxMedia/"
                    }
                ]
            }
        }
    }
}